{
    "courses": [{
            "title": "Angular 8",
            "price": "1200",
            "img": "https://upload.wikimedia.org/wikipedia/commons/thumb/c/cf/Angular_full_color_logo.svg/1200px-Angular_full_color_logo.svg.png",
            "id": "7aeb1b18-089b-4987-a879-6c4b250ce34f",
            "action": "",
            "count": 2
        },
        {
            "title": "Vue.js",
            "price": "1500",
            "img": "https://upload.wikimedia.org/wikipedia/commons/thumb/9/95/Vue.js_Logo_2.svg/1200px-Vue.js_Logo_2.svg.png",
            "id": "0e95070b-6c36-4b1e-8cde-6489d48963da",
            "action": "",
            "count": 1
        }
    ],
    "price": 3900
}